{ "backgroundcolor":"#000000",
 "compressionlevel":-1,
 "editorsettings":
    {
     "export":
        {
         "target":"."
        }
    },
 "height":100,
 "infinite":false,
 "layers":[
        {
         "compression":"zlib",
         "data":"eJztm0FuwjAQRXOWnKhHySpSWXVTibvCrhcoEYo6Mjh2XHs8mbwvPSHhYMLLMBpS9T4MX3cAAAAAAAAAAAAAAAAAAPgvg6D3uXgGz3j2BJ7x7Ak849kTeMazJ\/CMZ0\/gGc+ewLMhzwPZFTzrBM86wbNO8KwTPOsEzzrBs060Pc9jGo\/Bs07wrBM86wTPOtH2fBmfXB98C67j35rH9PK81O0kmPHcxPOSOXjEcxvPS2Q\/jnmeKrmvtU9JqGed0J91wryhE+pZJ0frz5\/jk0sG67EWcoR5QwbPeaGebfbnSTw\/jWWewz16xPq80dPz1t456zLUs06s92c8l2XvvNHCs+xXWt6t13OLnMlz6e\/BadxPaj+NWJ83ltR2QT3r9A2ZLc+XoBZW5Fy3tS5Df44ft15\/mVm8JrUuY33eaJ2U5yVhPUxj3roM9Rw\/borUQ+g5ti5ztP5c+z6S93ou\/XtKDc9n6s9HqOczzRs9f3d7qGd5XrG19bO0vI\/kvT+\/Oz+L9bzG+7xBPZdl77zR23Pv\/nx7rN\/SWl8i6zkkZ96okdy+UWveuL13aNqz5n3RWvXc0\/PH8Iq1eq7Vn3t4PlJqzRutPef8L4pljlLPvT3V8Ny7PycUu\/Bs4f7Gz2M9hhfPYa3GsuVipYVneKG4bxg49yMReg3Bc2fPuM4n4TjpGef6nnGt5xnfup5xree5xHXu694dZ\/VaZzj+t+fcz517vLXvVs579vAcvH\/1vTWuwc79u3k+KXg24PkX3+jIpQ==",
         "encoding":"base64",
         "height":100,
         "id":1,
         "name":"back",
         "opacity":0.5,
         "type":"tilelayer",
         "visible":true,
         "width":90,
         "x":0,
         "y":0
        }, 
        {
         "compression":"zlib",
         "data":"eJzt20FuwyAQQFGfxSfMylLdTTe5WXc9Spe9QBs1qBRjTMjAMOY\/adQqOBiPxoTQepoAAAAAAAAAAAAAAAAAAAAAAAAAAAAAQN46\/8ZrJFwbnpfKJXmW43K5RII8yyHPbTBv9GmN1HtJ+H1gizy3cZnlA9Byu9evgrFQz1Evs3xgizy34c8bpXNI2Ae2Lt7arHStINHH2ZHnNiTueeaNPFr7Hql98px2a97v0dreHONeP2q3RivP6876xa\/nVLs1mnkO5\/MlyHOq3Zqa83PqHnfnXIKf65zXbkm4Voh97hxF2MfH9Bcpfr78ug3zvNduieb6eaR6rpHnR+p5lPlZc190pPVGjf263HoeCfuibdTYF6Wet9iva0NzvTES9kXtop5xJtQzcG6a+6Ij4XtKG3xP+e8z8pr\/d3e3h5jzXJv2cT3\/f0Asz379ud9zn0\/ROi425p7s5dl9\/oR5PnreSuu4cMxfUzx6chu72\/Ntlb+9vPiR6i\/n\/amQlnOuVJ5T\/cSOOzpn71FKe9zWopT2uK1FKe1xW4tnaI\/dSkj66e\/NC\/Vr6ymkaV9Pr1GL9nX1FjVpX1tPUVvpeEqOkzi\/xRzHPDoWqTFr5FUzz9rnP1vd9i43P+T2XL4Bo0uVoA==",
         "encoding":"base64",
         "height":100,
         "id":2,
         "name":"front",
         "opacity":1,
         "type":"tilelayer",
         "visible":true,
         "width":90,
         "x":0,
         "y":0
        }, 
        {
         "color":"#5555ff",
         "draworder":"topdown",
         "id":3,
         "name":"mods",
         "objects":[],
         "opacity":1,
         "type":"objectgroup",
         "visible":true,
         "x":0,
         "y":0
        }, 
        {
         "color":"#ff0000",
         "draworder":"topdown",
         "id":4,
         "name":"objects",
         "objects":[
                {
                 "gid":247,
                 "height":8,
                 "id":1006,
                 "name":"",
                 "rotation":0,
                 "type":"",
                 "visible":true,
                 "width":8,
                 "x":664,
                 "y":688
                }, 
                {
                 "gid":8854,
                 "height":40,
                 "id":1009,
                 "name":"",
                 "properties":[
                        {
                         "name":"parameters",
                         "type":"string",
                         "value":"{\"treasurePools\":[\"basicTreasure\"]}"
                        }],
                 "rotation":0,
                 "type":"",
                 "visible":true,
                 "width":16,
                 "x":160,
                 "y":656
                }, 
                {
                 "gid":247,
                 "height":8,
                 "id":1034,
                 "name":"",
                 "rotation":0,
                 "type":"",
                 "visible":true,
                 "width":8,
                 "x":48,
                 "y":688
                }, 
                {
                 "gid":8864,
                 "height":8,
                 "id":1035,
                 "name":"",
                 "rotation":0,
                 "type":"",
                 "visible":true,
                 "width":24,
                 "x":192,
                 "y":360
                }, 
                {
                 "gid":8864,
                 "height":8,
                 "id":1036,
                 "name":"",
                 "rotation":0,
                 "type":"",
                 "visible":true,
                 "width":24,
                 "x":192,
                 "y":672
                }, 
                {
                 "gid":2147489631,
                 "height":20,
                 "id":1043,
                 "name":"",
                 "rotation":0,
                 "type":"",
                 "visible":true,
                 "width":16,
                 "x":144,
                 "y":656
                }, 
                {
                 "gid":5882,
                 "height":16,
                 "id":1045,
                 "name":"",
                 "rotation":0,
                 "type":"",
                 "visible":true,
                 "width":32,
                 "x":472,
                 "y":656
                }, 
                {
                 "gid":6971,
                 "height":16,
                 "id":1046,
                 "name":"",
                 "rotation":0,
                 "type":"",
                 "visible":true,
                 "width":8,
                 "x":320,
                 "y":464
                }, 
                {
                 "gid":7052,
                 "height":16,
                 "id":1047,
                 "name":"",
                 "rotation":0,
                 "type":"",
                 "visible":true,
                 "width":8,
                 "x":312,
                 "y":512
                }, 
                {
                 "gid":8864,
                 "height":8,
                 "id":1048,
                 "name":"",
                 "rotation":0,
                 "type":"",
                 "visible":true,
                 "width":24,
                 "x":272,
                 "y":672
                }, 
                {
                 "gid":8864,
                 "height":8,
                 "id":1049,
                 "name":"",
                 "rotation":0,
                 "type":"",
                 "visible":true,
                 "width":24,
                 "x":352,
                 "y":672
                }, 
                {
                 "gid":8864,
                 "height":8,
                 "id":1050,
                 "name":"",
                 "rotation":0,
                 "type":"",
                 "visible":true,
                 "width":24,
                 "x":432,
                 "y":672
                }, 
                {
                 "gid":8864,
                 "height":8,
                 "id":1052,
                 "name":"",
                 "rotation":0,
                 "type":"",
                 "visible":true,
                 "width":24,
                 "x":336,
                 "y":456
                }, 
                {
                 "gid":8841,
                 "height":24,
                 "id":1057,
                 "name":"",
                 "rotation":0,
                 "type":"",
                 "visible":true,
                 "width":56,
                 "x":320,
                 "y":512
                }, 
                {
                 "gid":8841,
                 "height":24,
                 "id":1058,
                 "name":"",
                 "rotation":0,
                 "type":"",
                 "visible":true,
                 "width":56,
                 "x":320,
                 "y":488
                }, 
                {
                 "gid":8864,
                 "height":8,
                 "id":1062,
                 "name":"",
                 "rotation":0,
                 "type":"",
                 "visible":true,
                 "width":24,
                 "x":336,
                 "y":576
                }, 
                {
                 "gid":8852,
                 "height":40,
                 "id":1065,
                 "name":"",
                 "properties":[
                        {
                         "name":"parameters",
                         "type":"string",
                         "value":"{\"treasurePools\":[\"basicChestTreasure\"]}"
                        }],
                 "rotation":0,
                 "type":"",
                 "visible":true,
                 "width":48,
                 "x":304,
                 "y":632
                }, 
                {
                 "gid":8855,
                 "height":16,
                 "id":1066,
                 "name":"",
                 "rotation":0,
                 "type":"",
                 "visible":true,
                 "width":16,
                 "x":312,
                 "y":592
                }, 
                {
                 "gid":8845,
                 "height":16,
                 "id":1067,
                 "name":"",
                 "properties":[
                        {
                         "name":"parameters",
                         "type":"string",
                         "value":"{\"treasurePools\":[\"basicTreasure\"]}"
                        }],
                 "rotation":0,
                 "type":"",
                 "visible":true,
                 "width":24,
                 "x":352,
                 "y":632
                }, 
                {
                 "gid":8870,
                 "height":16,
                 "id":1068,
                 "name":"",
                 "rotation":0,
                 "type":"",
                 "visible":true,
                 "width":24,
                 "x":352,
                 "y":616
                }, 
                {
                 "gid":8854,
                 "height":40,
                 "id":1069,
                 "name":"",
                 "properties":[
                        {
                         "name":"parameters",
                         "type":"string",
                         "value":"{\"treasurePools\":[\"basicTreasure\"]}"
                        }],
                 "rotation":0,
                 "type":"",
                 "visible":true,
                 "width":16,
                 "x":176,
                 "y":656
                }, 
                {
                 "gid":7330,
                 "height":16,
                 "id":1071,
                 "name":"",
                 "rotation":0,
                 "type":"",
                 "visible":true,
                 "width":16,
                 "x":520,
                 "y":672
                }, 
                {
                 "gid":7363,
                 "height":16,
                 "id":1072,
                 "name":"",
                 "rotation":0,
                 "type":"",
                 "visible":true,
                 "width":16,
                 "x":536,
                 "y":672
                }, 
                {
                 "gid":8864,
                 "height":8,
                 "id":1073,
                 "name":"",
                 "rotation":0,
                 "type":"",
                 "visible":true,
                 "width":24,
                 "x":528,
                 "y":488
                }, 
                {
                 "gid":8864,
                 "height":8,
                 "id":1074,
                 "name":"",
                 "rotation":0,
                 "type":"",
                 "visible":true,
                 "width":24,
                 "x":592,
                 "y":488
                }],
         "opacity":1,
         "type":"objectgroup",
         "visible":true,
         "x":0,
         "y":0
        }, 
        {
         "color":"#ffff00",
         "draworder":"topdown",
         "id":5,
         "name":"wiring - lights & guns",
         "objects":[],
         "opacity":1,
         "type":"objectgroup",
         "visible":true,
         "x":0,
         "y":0
        }, 
        {
         "color":"#ff0000",
         "draworder":"topdown",
         "id":6,
         "name":"monsters & npcs",
         "objects":[
                {
                 "height":8,
                 "id":995,
                 "name":"",
                 "properties":[
                        {
                         "name":"monster",
                         "type":"string",
                         "value":"arcana_monster_GS8Scout"
                        }],
                 "rotation":0,
                 "type":"",
                 "visible":true,
                 "width":8,
                 "x":200,
                 "y":592
                }, 
                {
                 "height":8,
                 "id":1031,
                 "name":"",
                 "properties":[
                        {
                         "name":"npc",
                         "type":"string",
                         "value":"human"
                        }, 
                        {
                         "name":"typeName",
                         "type":"string",
                         "value":"arcana_npc_workshop_section8Officer"
                        }],
                 "rotation":0,
                 "type":"",
                 "visible":true,
                 "width":8,
                 "x":560,
                 "y":648
                }, 
                {
                 "height":8,
                 "id":1039,
                 "name":"",
                 "properties":[
                        {
                         "name":"npc",
                         "type":"string",
                         "value":"human"
                        }, 
                        {
                         "name":"typeName",
                         "type":"string",
                         "value":"arcana_npc_workshop_section8Assembler"
                        }],
                 "rotation":0,
                 "type":"",
                 "visible":true,
                 "width":8,
                 "x":304,
                 "y":488
                }, 
                {
                 "gid":5693,
                 "height":40,
                 "id":1059,
                 "name":"",
                 "rotation":0,
                 "type":"",
                 "visible":true,
                 "width":48,
                 "x":256,
                 "y":632
                }, 
                {
                 "gid":5693,
                 "height":40,
                 "id":1060,
                 "name":"",
                 "rotation":0,
                 "type":"",
                 "visible":true,
                 "width":48,
                 "x":392,
                 "y":632
                }, 
                {
                 "gid":5693,
                 "height":40,
                 "id":1064,
                 "name":"",
                 "rotation":0,
                 "type":"",
                 "visible":true,
                 "width":48,
                 "x":392,
                 "y":512
                }],
         "opacity":1,
         "type":"objectgroup",
         "visible":true,
         "x":0,
         "y":0
        }, 
        {
         "color":"#00ffff",
         "draworder":"topdown",
         "id":7,
         "name":"wiring - locked door",
         "objects":[],
         "opacity":1,
         "type":"objectgroup",
         "visible":true,
         "x":0,
         "y":0
        }, 
        {
         "draworder":"topdown",
         "id":8,
         "name":"outside the map",
         "objects":[],
         "opacity":1,
         "type":"objectgroup",
         "visible":true,
         "x":0,
         "y":0
        }, 
        {
         "draworder":"topdown",
         "id":9,
         "name":"anchors etc",
         "objects":[
                {
                 "gid":240,
                 "height":8,
                 "id":713,
                 "name":"",
                 "rotation":0,
                 "type":"",
                 "visible":true,
                 "width":8,
                 "x":632,
                 "y":704
                }, 
                {
                 "gid":240,
                 "height":8,
                 "id":714,
                 "name":"",
                 "rotation":0,
                 "type":"",
                 "visible":true,
                 "width":8,
                 "x":80,
                 "y":704
                }, 
                {
                 "gid":251,
                 "height":8,
                 "id":723,
                 "name":"",
                 "rotation":0,
                 "type":"",
                 "visible":true,
                 "width":8,
                 "x":56,
                 "y":560
                }, 
                {
                 "gid":251,
                 "height":8,
                 "id":724,
                 "name":"",
                 "rotation":0,
                 "type":"",
                 "visible":true,
                 "width":8,
                 "x":72,
                 "y":688
                }, 
                {
                 "gid":251,
                 "height":8,
                 "id":725,
                 "name":"",
                 "rotation":0,
                 "type":"",
                 "visible":true,
                 "width":8,
                 "x":640,
                 "y":688
                }, 
                {
                 "gid":239,
                 "height":8,
                 "id":726,
                 "name":"",
                 "rotation":0,
                 "type":"",
                 "visible":true,
                 "width":8,
                 "x":632,
                 "y":688
                }, 
                {
                 "gid":239,
                 "height":8,
                 "id":727,
                 "name":"",
                 "rotation":0,
                 "type":"",
                 "visible":true,
                 "width":8,
                 "x":656,
                 "y":552
                }, 
                {
                 "gid":239,
                 "height":8,
                 "id":731,
                 "name":"",
                 "rotation":0,
                 "type":"",
                 "visible":true,
                 "width":8,
                 "x":56,
                 "y":552
                }, 
                {
                 "gid":239,
                 "height":8,
                 "id":732,
                 "name":"",
                 "rotation":0,
                 "type":"",
                 "visible":true,
                 "width":8,
                 "x":80,
                 "y":688
                }, 
                {
                 "gid":251,
                 "height":8,
                 "id":734,
                 "name":"",
                 "rotation":0,
                 "type":"",
                 "visible":true,
                 "width":8,
                 "x":64,
                 "y":288
                }, 
                {
                 "gid":251,
                 "height":8,
                 "id":735,
                 "name":"",
                 "rotation":0,
                 "type":"",
                 "visible":true,
                 "width":8,
                 "x":648,
                 "y":288
                }, 
                {
                 "gid":239,
                 "height":8,
                 "id":736,
                 "name":"",
                 "rotation":0,
                 "type":"",
                 "visible":true,
                 "width":8,
                 "x":656,
                 "y":288
                }, 
                {
                 "gid":239,
                 "height":8,
                 "id":737,
                 "name":"",
                 "rotation":0,
                 "type":"",
                 "visible":true,
                 "width":8,
                 "x":56,
                 "y":288
                }, 
                {
                 "gid":251,
                 "height":8,
                 "id":762,
                 "name":"",
                 "rotation":0,
                 "type":"",
                 "visible":true,
                 "width":8,
                 "x":656,
                 "y":560
                }],
         "opacity":1,
         "type":"objectgroup",
         "visible":true,
         "x":0,
         "y":0
        }, 
        {
         "draworder":"topdown",
         "id":10,
         "name":"items",
         "objects":[],
         "opacity":1,
         "type":"objectgroup",
         "visible":true,
         "x":0,
         "y":0
        }],
 "nextlayerid":11,
 "nextobjectid":1075,
 "orientation":"orthogonal",
 "renderorder":"right-down",
 "tiledversion":"1.4.3",
 "tileheight":8,
 "tilesets":[
        {
         "firstgid":1,
         "source":"..\/..\/..\/..\/..\/assets\/packed\/tilesets\/packed\/materials.json"
        }, 
        {
         "firstgid":198,
         "source":"..\/..\/..\/..\/..\/assets\/packed\/tilesets\/packed\/supports.json"
        }, 
        {
         "firstgid":235,
         "source":"..\/..\/..\/..\/..\/assets\/packed\/tilesets\/packed\/miscellaneous.json"
        }, 
        {
         "firstgid":259,
         "source":"..\/..\/..\/..\/..\/assets\/packed\/tilesets\/packed\/liquids.json"
        }, 
        {
         "firstgid":287,
         "source":"..\/..\/..\/..\/..\/assets\/packed\/tilesets\/packed\/objects-by-race\/generic.json"
        }, 
        {
         "firstgid":2271,
         "source":"..\/..\/..\/..\/..\/assets\/packed\/tilesets\/packed\/objects-by-race\/ancient.json"
        }, 
        {
         "firstgid":2434,
         "source":"..\/..\/..\/..\/..\/assets\/packed\/tilesets\/packed\/objects-by-race\/apex.json"
        }, 
        {
         "firstgid":2805,
         "source":"..\/..\/..\/..\/..\/assets\/packed\/tilesets\/packed\/objects-by-race\/avian.json"
        }, 
        {
         "firstgid":3110,
         "source":"..\/..\/..\/..\/..\/assets\/packed\/tilesets\/packed\/objects-by-race\/floran.json"
        }, 
        {
         "firstgid":3305,
         "source":"..\/..\/..\/..\/..\/assets\/packed\/tilesets\/packed\/objects-by-race\/glitch.json"
        }, 
        {
         "firstgid":3531,
         "source":"..\/..\/..\/..\/..\/assets\/packed\/tilesets\/packed\/objects-by-race\/human.json"
        }, 
        {
         "firstgid":3819,
         "source":"..\/..\/..\/..\/..\/assets\/packed\/tilesets\/packed\/objects-by-race\/hylotl.json"
        }, 
        {
         "firstgid":4051,
         "source":"..\/..\/..\/..\/..\/assets\/packed\/tilesets\/packed\/objects-by-race\/novakid.json"
        }, 
        {
         "firstgid":4115,
         "source":"..\/..\/..\/..\/..\/assets\/packed\/tilesets\/packed\/objects-by-category\/crafting.json"
        }, 
        {
         "firstgid":4195,
         "source":"..\/..\/..\/..\/..\/assets\/packed\/tilesets\/packed\/objects-by-category\/decorative.json"
        }, 
        {
         "firstgid":5636,
         "source":"..\/..\/..\/..\/..\/assets\/packed\/tilesets\/packed\/objects-by-category\/door.json"
        }, 
        {
         "firstgid":5768,
         "source":"..\/..\/..\/..\/..\/assets\/packed\/tilesets\/packed\/objects-by-category\/farmable.json"
        }, 
        {
         "firstgid":5843,
         "source":"..\/..\/..\/..\/..\/assets\/packed\/tilesets\/packed\/objects-by-category\/furniture.json"
        }, 
        {
         "firstgid":6197,
         "source":"..\/..\/..\/..\/..\/assets\/packed\/tilesets\/packed\/objects-by-category\/light.json"
        }, 
        {
         "firstgid":6655,
         "source":"..\/..\/..\/..\/..\/assets\/packed\/tilesets\/packed\/objects-by-category\/other.json"
        }, 
        {
         "firstgid":6967,
         "source":"..\/..\/..\/..\/..\/assets\/packed\/tilesets\/packed\/objects-by-category\/pot.json"
        }, 
        {
         "firstgid":7264,
         "source":"..\/..\/..\/..\/..\/assets\/packed\/tilesets\/packed\/objects-by-category\/sapling.json"
        }, 
        {
         "firstgid":7265,
         "source":"..\/..\/..\/..\/..\/assets\/packed\/tilesets\/packed\/objects-by-category\/spawner.json"
        }, 
        {
         "firstgid":7281,
         "source":"..\/..\/..\/..\/..\/assets\/packed\/tilesets\/packed\/objects-by-category\/storage.json"
        }, 
        {
         "firstgid":7515,
         "source":"..\/..\/..\/..\/..\/assets\/packed\/tilesets\/packed\/objects-by-category\/teleporter.json"
        }, 
        {
         "firstgid":7557,
         "source":"..\/..\/..\/..\/..\/assets\/packed\/tilesets\/packed\/objects-by-category\/tools.json"
        }, 
        {
         "firstgid":7562,
         "source":"..\/..\/..\/..\/..\/assets\/packed\/tilesets\/packed\/objects-by-category\/trap.json"
        }, 
        {
         "firstgid":7766,
         "source":"..\/..\/..\/..\/..\/assets\/packed\/tilesets\/packed\/objects-by-category\/wire.json"
        }, 
        {
         "firstgid":7988,
         "source":"..\/..\/..\/..\/..\/assets\/packed\/tilesets\/packed\/objects-by-type\/container.json"
        }, 
        {
         "firstgid":8273,
         "source":"..\/..\/..\/..\/..\/assets\/packed\/tilesets\/packed\/objects-by-type\/farmable.json"
        }, 
        {
         "firstgid":8351,
         "source":"..\/..\/..\/..\/..\/assets\/packed\/tilesets\/packed\/objects-by-type\/loungeable.json"
        }, 
        {
         "firstgid":8632,
         "source":"..\/..\/..\/..\/..\/assets\/packed\/tilesets\/packed\/objects-by-type\/noisy.json"
        }, 
        {
         "firstgid":8673,
         "source":"..\/..\/..\/..\/..\/assets\/packed\/tilesets\/packed\/objects-by-type\/teleporter.json"
        }, 
        {
         "firstgid":8700,
         "source":"..\/..\/..\/..\/..\/assets\/packed\/tilesets\/packed\/huge-objects.json"
        }, 
        {
         "firstgid":8801,
         "source":"..\/..\/tilesets\/tiles\/aeon_tiles\/aeon_tiles.json"
        }, 
        {
         "firstgid":8805,
         "source":"..\/..\/tilesets\/tiles\/timeless_tiles\/timeless_tiles.json"
        }, 
        {
         "firstgid":8807,
         "source":"..\/..\/tilesets\/tiles\/arcana_platforms\/arcana_platforms.json"
        }, 
        {
         "firstgid":8809,
         "source":"..\/..\/tilesets\/tiles\/cerueon_tiles\/cerueon_tiles.json"
        }, 
        {
         "firstgid":8811,
         "source":"..\/..\/tilesets\/tiles\/orion_tiles\/orion_tiles.json"
        }, 
        {
         "firstgid":8825,
         "source":"..\/..\/tilesets\/tiles\/workshop_tiles\/workshop_tiles.json"
        }, 
        {
         "firstgid":8835,
         "source":"..\/..\/tilesets\/tiles\/horizon_tiles\/horizon_tiles.json"
        }, 
        {
         "firstgid":8841,
         "source":"..\/..\/tilesets\/objects\/workshop_objects\/workshop_objects.json"
        }],
 "tilewidth":8,
 "type":"map",
 "version":1.4,
 "width":90
}