{ "backgroundcolor":"#000000",
 "compressionlevel":-1,
 "editorsettings":
    {
     "export":
        {
         "target":"."
        }
    },
 "height":50,
 "infinite":false,
 "layers":[
        {
         "compression":"zlib",
         "data":"eJztmM2N2zAQhVnAHo3cckkDPhgIkFpSQzrQwTUY8GEBnbwNBGlib6kpHoAPGQ9mKFIaUfLuPOCBFi3+fRz+2O8pnd\/D4R06hZoUHH0UHH0UHH0UHH0UHH0UHH0UHH0UHH0UHH0UHH0UHH0UHH0UHH3Ug+No5HGvrbXb2IIj2P361o\/lR+MIfmD4kr220Ic\/DW5RLccl84myl2ywA8seQju\/G9yi3hyJHaXDgvrmiOKrhSFcG5e9OJIv6XEvHMT3a4rqb1nT1tq2+tkzHikdsjlb7Jclne7+XvCpsg\/07lmUtZ5L9Uj15EjiHLFPXpJd\/yn7mstdFSMf75b6cLvP18807Zsxr3vhiGfEIWLUEn1XikNpqy704a2S41sHjq1MS\/cevsalXtNjDE7FIz6\/KnUdcvrMHDEGrGNwozHjLqQJHI\/Z\/PPRyN87xwP7PJcjYpGEOJQMB5aC49fsQTxrebwcr+8jceTC+LV8pHvhyMerjYW0N47Uf74+h4kyMo+XO6b\/PJ6Z40GkkMWQRP3n58USjtf0yJFM95lzmvZN4Yg6NLVw5PtcjSRHpK0c+Vls3XXkec05jqz\/9Fxzf9LikTOQPNfmqLVd+h2oceRnsXXvkee15PiS2\/\/RYMiLo8XDEn9PlsMZ\/eXeBpn\/ZzYmfX9svYfL\/RFtjQqrGo5yPBqDKY6Yy7FQhxR\/j98ZMR7NaKeH5nDEGsJ4Wjgidvh\/huCJ8cs+Uh5vF+VLDMl\/O7qWI8ZgzTvfmyyO9\/aSbL\/EYIrLHvhpHL3qbOEYns3R8ub93ptncvxMPGs4mPtjxKUvxwmeW4+xK0eLRS3DGeu9txfH05TnsHpSpqvwW5vhjpm6cezJbwnLnnNgtaP1YSt+rVxr3\/fgbNW\/NZu5LLfuRzj8Wf0PVK86jQ==",
         "encoding":"base64",
         "height":50,
         "id":1,
         "name":"back",
         "opacity":0.5,
         "type":"tilelayer",
         "visible":true,
         "width":82,
         "x":0,
         "y":0
        }, 
        {
         "compression":"zlib",
         "data":"eJztmEFuwjAQRd0Vq26z7KJXiITE3bLwJbpg3QugHsSco7doDDYMxmNPHIcS\/J\/0FWLi8cwfJ0EoBQAAAAAAAAAAAAAAAADk+amoljlUVKvU9LAVL+19R+vM+ZG6f6Ve+jivhtSHftRm1DDqi2hw470gRgvPTG6fWX8GYYzBXd\/6O8d68P153Wf9jDh+39p4pXHWiHbaq3Pd\/lgCnb8nsVvC1v3hjs8QZ63Y+3Cr5M9EDjt\/6+K1CHysg39HzH031IoDAAAAgFvs\/w30d4891+p8LpVW1\/8z\/O+eTeL6gRzf35avsRbdWGpKvdNAPlvt1KnWmzFu3ETGjuOY1Y6oc\/Pp+rW9NC7+73isoU4gX6cJ6jVnb\/QuGE\/pGLnee2mE+dC8\/DxOHLRHc\/w7BuJyzOSqqUJ\/DPPZ7bVLnJQ3hXllfSTxT17SOqZ6F8nnFCdVkyF9DH001\/Ebn7xcv3TojwnWSKyb+r7IR65fZC1N12N6GfNCEpudH\/MpWPcuL8k+zOU11cecn1y8jHdJ\/xL9Dz1k\/YiN57wLfcqdl\/jI+SmQTuVKv+f2Vc7vWH3SGJK8Yop5UYLUw2Df3d2Dqf5Kao7NndILacw5XkmZsj9zeXLPgCnecftbsHZSj6Q0xwV06cFc\/ReleT7CX26dWA7PxtQ+L+EzF39trDVvAF6FP4xISh0=",
         "encoding":"base64",
         "height":50,
         "id":2,
         "name":"front",
         "opacity":1,
         "type":"tilelayer",
         "visible":true,
         "width":82,
         "x":0,
         "y":0
        }, 
        {
         "color":"#5555ff",
         "draworder":"topdown",
         "id":3,
         "name":"mods",
         "objects":[],
         "opacity":1,
         "type":"objectgroup",
         "visible":true,
         "x":0,
         "y":0
        }, 
        {
         "color":"#ff0000",
         "draworder":"topdown",
         "id":4,
         "name":"objects",
         "objects":[
                {
                 "gid":8837,
                 "height":24,
                 "id":1051,
                 "name":"",
                 "rotation":0,
                 "type":"",
                 "visible":true,
                 "width":24,
                 "x":216,
                 "y":280
                }, 
                {
                 "gid":2147490111,
                 "height":40,
                 "id":1052,
                 "name":"",
                 "rotation":0,
                 "type":"",
                 "visible":true,
                 "width":16,
                 "x":184,
                 "y":288
                }, 
                {
                 "gid":8837,
                 "height":24,
                 "id":1053,
                 "name":"",
                 "rotation":0,
                 "type":"",
                 "visible":true,
                 "width":24,
                 "x":584,
                 "y":288
                }, 
                {
                 "gid":6463,
                 "height":40,
                 "id":1054,
                 "name":"",
                 "rotation":0,
                 "type":"",
                 "visible":true,
                 "width":16,
                 "x":544,
                 "y":288
                }, 
                {
                 "gid":8836,
                 "height":40,
                 "id":1055,
                 "name":"",
                 "rotation":0,
                 "type":"",
                 "visible":true,
                 "width":24,
                 "x":472,
                 "y":224
                }, 
                {
                 "gid":8836,
                 "height":40,
                 "id":1056,
                 "name":"",
                 "rotation":0,
                 "type":"",
                 "visible":true,
                 "width":24,
                 "x":504,
                 "y":224
                }, 
                {
                 "gid":5664,
                 "height":40,
                 "id":1057,
                 "name":"",
                 "rotation":0,
                 "type":"",
                 "visible":true,
                 "width":40,
                 "x":256,
                 "y":272
                }, 
                {
                 "gid":5664,
                 "height":40,
                 "id":1058,
                 "name":"",
                 "rotation":0,
                 "type":"",
                 "visible":true,
                 "width":40,
                 "x":400,
                 "y":272
                }, 
                {
                 "gid":6460,
                 "height":24,
                 "id":1059,
                 "name":"",
                 "rotation":0,
                 "type":"",
                 "visible":true,
                 "width":16,
                 "x":296,
                 "y":208
                }, 
                {
                 "gid":6460,
                 "height":24,
                 "id":1060,
                 "name":"",
                 "rotation":0,
                 "type":"",
                 "visible":true,
                 "width":16,
                 "x":384,
                 "y":208
                }, 
                {
                 "gid":6265,
                 "height":16,
                 "id":1061,
                 "name":"",
                 "rotation":0,
                 "type":"",
                 "visible":true,
                 "width":16,
                 "x":248,
                 "y":216
                }, 
                {
                 "gid":6265,
                 "height":16,
                 "id":1062,
                 "name":"",
                 "rotation":0,
                 "type":"",
                 "visible":true,
                 "width":16,
                 "x":432,
                 "y":216
                }, 
                {
                 "gid":7348,
                 "height":16,
                 "id":1063,
                 "name":"",
                 "properties":[
                        {
                         "name":"parameters",
                         "type":"string",
                         "value":"{\"treasurePools\":[\"basicTreasure\"]}"
                        }],
                 "rotation":0,
                 "type":"",
                 "visible":true,
                 "width":16,
                 "x":368,
                 "y":232
                }, 
                {
                 "gid":2147491049,
                 "height":40,
                 "id":1064,
                 "name":"",
                 "properties":[
                        {
                         "name":"parameters",
                         "type":"string",
                         "value":"{\"treasurePools\":[\"basicTreasure\"]}"
                        }],
                 "rotation":0,
                 "type":"",
                 "visible":true,
                 "width":24,
                 "x":360,
                 "y":272
                }, 
                {
                 "gid":3363,
                 "height":24,
                 "id":1066,
                 "name":"",
                 "rotation":0,
                 "type":"",
                 "visible":true,
                 "width":16,
                 "x":200,
                 "y":280
                }, 
                {
                 "gid":3377,
                 "height":16,
                 "id":1067,
                 "name":"",
                 "rotation":0,
                 "type":"",
                 "visible":true,
                 "width":16,
                 "x":528,
                 "y":288
                }, 
                {
                 "gid":3378,
                 "height":16,
                 "id":1068,
                 "name":"",
                 "rotation":0,
                 "type":"",
                 "visible":true,
                 "width":48,
                 "x":448,
                 "y":272
                }, 
                {
                 "gid":3484,
                 "height":8,
                 "id":1069,
                 "name":"",
                 "rotation":0,
                 "type":"",
                 "visible":true,
                 "width":16,
                 "x":432,
                 "y":272
                }, 
                {
                 "gid":2147487132,
                 "height":8,
                 "id":1070,
                 "name":"",
                 "rotation":0,
                 "type":"",
                 "visible":true,
                 "width":16,
                 "x":496,
                 "y":272
                }, 
                {
                 "gid":3452,
                 "height":8,
                 "id":1071,
                 "name":"",
                 "rotation":0,
                 "type":"",
                 "visible":true,
                 "width":16,
                 "x":464,
                 "y":256
                }, 
                {
                 "gid":3496,
                 "height":24,
                 "id":1072,
                 "name":"",
                 "rotation":0,
                 "type":"",
                 "visible":true,
                 "width":16,
                 "x":448,
                 "y":200
                }, 
                {
                 "gid":3406,
                 "height":28,
                 "id":1073,
                 "name":"",
                 "rotation":0,
                 "type":"",
                 "visible":true,
                 "width":32,
                 "x":328,
                 "y":224
                }, 
                {
                 "gid":4142,
                 "height":36,
                 "id":1074,
                 "name":"",
                 "rotation":0,
                 "type":"",
                 "visible":true,
                 "width":32,
                 "x":288,
                 "y":272
                }, 
                {
                 "gid":2147487807,
                 "height":24,
                 "id":1075,
                 "name":"",
                 "rotation":0,
                 "type":"",
                 "visible":true,
                 "width":24,
                 "x":384,
                 "y":272
                }, 
                {
                 "gid":2147489521,
                 "height":16,
                 "id":1076,
                 "name":"",
                 "rotation":0,
                 "type":"",
                 "visible":true,
                 "width":32,
                 "x":328,
                 "y":272
                }, 
                {
                 "gid":6971,
                 "height":16,
                 "id":1079,
                 "name":"",
                 "rotation":0,
                 "type":"",
                 "visible":true,
                 "width":8,
                 "x":360,
                 "y":232
                }, 
                {
                 "gid":7062,
                 "height":16,
                 "id":1080,
                 "name":"",
                 "rotation":0,
                 "type":"",
                 "visible":true,
                 "width":8,
                 "x":352,
                 "y":256
                }, 
                {
                 "gid":7052,
                 "height":16,
                 "id":1081,
                 "name":"",
                 "rotation":0,
                 "type":"",
                 "visible":true,
                 "width":8,
                 "x":456,
                 "y":256
                }],
         "opacity":1,
         "type":"objectgroup",
         "visible":true,
         "x":0,
         "y":0
        }, 
        {
         "color":"#ffff00",
         "draworder":"topdown",
         "id":5,
         "name":"wiring - lights & guns",
         "objects":[],
         "opacity":1,
         "type":"objectgroup",
         "visible":true,
         "x":0,
         "y":0
        }, 
        {
         "color":"#ff0000",
         "draworder":"topdown",
         "id":6,
         "name":"monsters & npcs",
         "objects":[
                {
                 "height":8,
                 "id":1077,
                 "name":"",
                 "properties":[
                        {
                         "name":"npc",
                         "type":"string",
                         "value":"human"
                        }, 
                        {
                         "name":"typeName",
                         "type":"string",
                         "value":"villager"
                        }],
                 "rotation":0,
                 "type":"",
                 "visible":true,
                 "width":8,
                 "x":504,
                 "y":248
                }, 
                {
                 "height":8,
                 "id":1078,
                 "name":"",
                 "properties":[
                        {
                         "name":"npc",
                         "type":"string",
                         "value":"hylotl"
                        }, 
                        {
                         "name":"typeName",
                         "type":"string",
                         "value":"chefmerchant"
                        }],
                 "rotation":0,
                 "type":"",
                 "visible":true,
                 "width":8,
                 "x":376,
                 "y":248
                }, 
                {
                 "height":8,
                 "id":1082,
                 "name":"",
                 "properties":[
                        {
                         "name":"monster",
                         "type":"string",
                         "value":"pinfriend"
                        }, 
                        {
                         "name":"parameters",
                         "type":"string",
                         "value":"{ \"persistent\" : true }"
                        }, 
                        {
                         "name":"seed",
                         "type":"string",
                         "value":"5"
                        }],
                 "rotation":0,
                 "type":"",
                 "visible":true,
                 "width":8,
                 "x":248,
                 "y":256
                }],
         "opacity":1,
         "type":"objectgroup",
         "visible":true,
         "x":0,
         "y":0
        }, 
        {
         "color":"#00ffff",
         "draworder":"topdown",
         "id":7,
         "name":"wiring - locked door",
         "objects":[],
         "opacity":1,
         "type":"objectgroup",
         "visible":true,
         "x":0,
         "y":0
        }, 
        {
         "draworder":"topdown",
         "id":8,
         "name":"outside the map",
         "objects":[],
         "opacity":1,
         "type":"objectgroup",
         "visible":true,
         "x":0,
         "y":0
        }, 
        {
         "draworder":"topdown",
         "id":9,
         "name":"anchors etc",
         "objects":[
                {
                 "gid":202,
                 "height":8,
                 "id":708,
                 "name":"",
                 "rotation":0,
                 "type":"",
                 "visible":true,
                 "width":8,
                 "x":624,
                 "y":24
                }, 
                {
                 "gid":202,
                 "height":8,
                 "id":709,
                 "name":"",
                 "rotation":0,
                 "type":"",
                 "visible":true,
                 "width":8,
                 "x":336,
                 "y":24
                }, 
                {
                 "gid":202,
                 "height":8,
                 "id":710,
                 "name":"",
                 "rotation":0,
                 "type":"",
                 "visible":true,
                 "width":8,
                 "x":24,
                 "y":24
                }, 
                {
                 "gid":202,
                 "height":8,
                 "id":711,
                 "name":"",
                 "rotation":0,
                 "type":"",
                 "visible":true,
                 "width":8,
                 "x":24,
                 "y":288
                }, 
                {
                 "gid":202,
                 "height":8,
                 "id":712,
                 "name":"",
                 "rotation":0,
                 "type":"",
                 "visible":true,
                 "width":8,
                 "x":624,
                 "y":288
                }, 
                {
                 "gid":203,
                 "height":8,
                 "id":713,
                 "name":"",
                 "rotation":0,
                 "type":"",
                 "visible":true,
                 "width":8,
                 "x":624,
                 "y":312
                }, 
                {
                 "gid":203,
                 "height":8,
                 "id":714,
                 "name":"",
                 "rotation":0,
                 "type":"",
                 "visible":true,
                 "width":8,
                 "x":24,
                 "y":312
                }, 
                {
                 "gid":202,
                 "height":8,
                 "id":715,
                 "name":"",
                 "rotation":0,
                 "type":"",
                 "visible":true,
                 "width":8,
                 "x":624,
                 "y":168
                }, 
                {
                 "gid":202,
                 "height":8,
                 "id":716,
                 "name":"",
                 "rotation":0,
                 "type":"",
                 "visible":true,
                 "width":8,
                 "x":24,
                 "y":160
                }, 
                {
                 "gid":214,
                 "height":8,
                 "id":725,
                 "name":"",
                 "rotation":0,
                 "type":"",
                 "visible":true,
                 "width":8,
                 "x":624,
                 "y":24
                }, 
                {
                 "gid":214,
                 "height":8,
                 "id":726,
                 "name":"",
                 "rotation":0,
                 "type":"",
                 "visible":true,
                 "width":8,
                 "x":336,
                 "y":24
                }, 
                {
                 "gid":214,
                 "height":8,
                 "id":727,
                 "name":"",
                 "rotation":0,
                 "type":"",
                 "visible":true,
                 "width":8,
                 "x":24,
                 "y":24
                }, 
                {
                 "gid":214,
                 "height":8,
                 "id":728,
                 "name":"",
                 "rotation":0,
                 "type":"",
                 "visible":true,
                 "width":8,
                 "x":24,
                 "y":160
                }, 
                {
                 "gid":214,
                 "height":8,
                 "id":729,
                 "name":"",
                 "rotation":0,
                 "type":"",
                 "visible":true,
                 "width":8,
                 "x":24,
                 "y":288
                }, 
                {
                 "gid":214,
                 "height":8,
                 "id":730,
                 "name":"",
                 "rotation":0,
                 "type":"",
                 "visible":true,
                 "width":8,
                 "x":624,
                 "y":288
                }, 
                {
                 "gid":214,
                 "height":8,
                 "id":731,
                 "name":"",
                 "rotation":0,
                 "type":"",
                 "visible":true,
                 "width":8,
                 "x":624,
                 "y":168
                }, 
                {
                 "gid":210,
                 "height":8,
                 "id":879,
                 "name":"",
                 "rotation":0,
                 "type":"",
                 "visible":true,
                 "width":8,
                 "x":16,
                 "y":288
                }, 
                {
                 "gid":210,
                 "height":8,
                 "id":880,
                 "name":"",
                 "rotation":0,
                 "type":"",
                 "visible":true,
                 "width":8,
                 "x":632,
                 "y":288
                }, 
                {
                 "height":192,
                 "id":1083,
                 "name":"",
                 "properties":[
                        {
                         "name":"stagehand",
                         "type":"string",
                         "value":"objecttracker"
                        }],
                 "rotation":0,
                 "type":"",
                 "visible":true,
                 "width":432,
                 "x":176,
                 "y":128
                }],
         "opacity":1,
         "type":"objectgroup",
         "visible":true,
         "x":0,
         "y":0
        }, 
        {
         "draworder":"topdown",
         "id":10,
         "name":"items",
         "objects":[],
         "opacity":1,
         "type":"objectgroup",
         "visible":true,
         "x":0,
         "y":0
        }],
 "nextlayerid":11,
 "nextobjectid":1084,
 "orientation":"orthogonal",
 "renderorder":"right-down",
 "tiledversion":"1.4.3",
 "tileheight":8,
 "tilesets":[
        {
         "firstgid":1,
         "source":"..\/..\/..\/..\/unpacked_files\/unpacked\/tilesets\/packed\/materials.json"
        }, 
        {
         "firstgid":198,
         "source":"..\/..\/..\/..\/unpacked_files\/unpacked\/tilesets\/packed\/miscellaneous.json"
        }, 
        {
         "firstgid":222,
         "source":"..\/..\/..\/..\/unpacked_files\/unpacked\/tilesets\/packed\/liquids.json"
        }, 
        {
         "firstgid":250,
         "source":"..\/..\/..\/..\/unpacked_files\/unpacked\/tilesets\/packed\/supports.json"
        }, 
        {
         "firstgid":287,
         "source":"..\/..\/..\/..\/unpacked_files\/unpacked\/tilesets\/packed\/objects-by-race\/generic.json"
        }, 
        {
         "firstgid":2271,
         "source":"..\/..\/..\/..\/unpacked_files\/unpacked\/tilesets\/packed\/objects-by-race\/ancient.json"
        }, 
        {
         "firstgid":2434,
         "source":"..\/..\/..\/..\/unpacked_files\/unpacked\/tilesets\/packed\/objects-by-race\/apex.json"
        }, 
        {
         "firstgid":2805,
         "source":"..\/..\/..\/..\/unpacked_files\/unpacked\/tilesets\/packed\/objects-by-race\/avian.json"
        }, 
        {
         "firstgid":3110,
         "source":"..\/..\/..\/..\/unpacked_files\/unpacked\/tilesets\/packed\/objects-by-race\/floran.json"
        }, 
        {
         "firstgid":3305,
         "source":"..\/..\/..\/..\/unpacked_files\/unpacked\/tilesets\/packed\/objects-by-race\/glitch.json"
        }, 
        {
         "firstgid":3531,
         "source":"..\/..\/..\/..\/unpacked_files\/unpacked\/tilesets\/packed\/objects-by-race\/human.json"
        }, 
        {
         "firstgid":3819,
         "source":"..\/..\/..\/..\/unpacked_files\/unpacked\/tilesets\/packed\/objects-by-race\/hylotl.json"
        }, 
        {
         "firstgid":4051,
         "source":"..\/..\/..\/..\/unpacked_files\/unpacked\/tilesets\/packed\/objects-by-race\/novakid.json"
        }, 
        {
         "firstgid":4115,
         "source":"..\/..\/..\/..\/unpacked_files\/unpacked\/tilesets\/packed\/objects-by-category\/crafting.json"
        }, 
        {
         "firstgid":4195,
         "source":"..\/..\/..\/..\/unpacked_files\/unpacked\/tilesets\/packed\/objects-by-category\/decorative.json"
        }, 
        {
         "firstgid":5636,
         "source":"..\/..\/..\/..\/unpacked_files\/unpacked\/tilesets\/packed\/objects-by-category\/door.json"
        }, 
        {
         "firstgid":5768,
         "source":"..\/..\/..\/..\/unpacked_files\/unpacked\/tilesets\/packed\/objects-by-category\/farmable.json"
        }, 
        {
         "firstgid":5843,
         "source":"..\/..\/..\/..\/unpacked_files\/unpacked\/tilesets\/packed\/objects-by-category\/furniture.json"
        }, 
        {
         "firstgid":6197,
         "source":"..\/..\/..\/..\/unpacked_files\/unpacked\/tilesets\/packed\/objects-by-category\/light.json"
        }, 
        {
         "firstgid":6655,
         "source":"..\/..\/..\/..\/unpacked_files\/unpacked\/tilesets\/packed\/objects-by-category\/other.json"
        }, 
        {
         "firstgid":6967,
         "source":"..\/..\/..\/..\/unpacked_files\/unpacked\/tilesets\/packed\/objects-by-category\/pot.json"
        }, 
        {
         "firstgid":7264,
         "source":"..\/..\/..\/..\/unpacked_files\/unpacked\/tilesets\/packed\/objects-by-category\/sapling.json"
        }, 
        {
         "firstgid":7265,
         "source":"..\/..\/..\/..\/unpacked_files\/unpacked\/tilesets\/packed\/objects-by-category\/spawner.json"
        }, 
        {
         "firstgid":7281,
         "source":"..\/..\/..\/..\/unpacked_files\/unpacked\/tilesets\/packed\/objects-by-category\/storage.json"
        }, 
        {
         "firstgid":7515,
         "source":"..\/..\/..\/..\/unpacked_files\/unpacked\/tilesets\/packed\/objects-by-category\/teleporter.json"
        }, 
        {
         "firstgid":7557,
         "source":"..\/..\/..\/..\/unpacked_files\/unpacked\/tilesets\/packed\/objects-by-category\/tools.json"
        }, 
        {
         "firstgid":7562,
         "source":"..\/..\/..\/..\/unpacked_files\/unpacked\/tilesets\/packed\/objects-by-category\/trap.json"
        }, 
        {
         "firstgid":7766,
         "source":"..\/..\/..\/..\/unpacked_files\/unpacked\/tilesets\/packed\/objects-by-category\/wire.json"
        }, 
        {
         "firstgid":7988,
         "source":"..\/..\/..\/..\/unpacked_files\/unpacked\/tilesets\/packed\/objects-by-type\/container.json"
        }, 
        {
         "firstgid":8273,
         "source":"..\/..\/..\/..\/unpacked_files\/unpacked\/tilesets\/packed\/objects-by-type\/farmable.json"
        }, 
        {
         "firstgid":8351,
         "source":"..\/..\/..\/..\/unpacked_files\/unpacked\/tilesets\/packed\/objects-by-type\/loungeable.json"
        }, 
        {
         "firstgid":8632,
         "source":"..\/..\/..\/..\/unpacked_files\/unpacked\/tilesets\/packed\/objects-by-type\/noisy.json"
        }, 
        {
         "firstgid":8673,
         "source":"..\/..\/..\/..\/unpacked_files\/unpacked\/tilesets\/packed\/objects-by-type\/teleporter.json"
        }, 
        {
         "firstgid":8700,
         "source":"..\/..\/..\/..\/unpacked_files\/unpacked\/tilesets\/packed\/huge-objects.json"
        }, 
        {
         "firstgid":8801,
         "source":"..\/..\/tilesets\/tiles\/arcana_tiles\/arcana_tiles.json"
        }, 
        {
         "firstgid":8822,
         "source":"..\/..\/tilesets\/objects\/springpalms_objects\/springpalms_objects.json"
        }, 
        {
         "firstgid":8830,
         "source":"..\/..\/tilesets\/objects\/solar_objects\/solar_objects.json"
        }, 
        {
         "firstgid":8843,
         "source":"..\/..\/tilesets\/tiles\/solar_tiles\/solar_tiles.json"
        }, 
        {
         "firstgid":8849,
         "source":"..\/..\/tilesets\/tiles\/solarized_tiles\/solarized_tiles.json"
        }, 
        {
         "firstgid":8852,
         "source":"..\/..\/tilesets\/tiles\/orion_tiles\/orion_tiles.json"
        }, 
        {
         "firstgid":8866,
         "source":"..\/..\/tilesets\/tiles\/painted_tiles\/painted_tiles.json"
        }, 
        {
         "firstgid":8903,
         "source":"..\/..\/tilesets\/objects\/luye_objects\/luye_objects.json"
        }],
 "tilewidth":8,
 "type":"map",
 "version":1.4,
 "width":82
}